<?xml version="1.0" encoding="UTF-8"?>
<OpenSearchDescription xmlns="http://a9.com/-/spec/opensearch/1.1/"
                       xmlns:moz="http://www.mozilla.org/2006/browser/search/">
  <ShortName>Redux 中文官网</ShortName>
  <Description>Search Redux 中文官网</Description>
  <InputEncoding>UTF-8</InputEncoding>
  <Image width="16" height="16" type="image/x-icon">https://camsong.github.io/redux-in-chinese/img/favicon/favicon.ico</Image>
  <Url type="text/html" method="get" template="https://camsong.github.io/redux-in-chinese/search?q={searchTerms}"/>
  <Url type="application/opensearchdescription+xml" rel="self" template="https://camsong.github.io/redux-in-chinese/opensearch.xml" />
  <moz:SearchForm>https://camsong.github.io/redux-in-chinese/</moz:SearchForm>
</OpenSearchDescription>